[
{
	"id": "eng/0",
	"body": "Choose the option nearest in meaning to the word(s) or phrase in italics (**).\n\nI cannot understand why Ali should serve in that *moribund* administration.",
	"options": {
		"a": "oppressive",
		"b": "prodigal",
		"c": "crumbling",
		"d": "purposeless"
	},
	"answer": "c"
},
{
	"id": "eng/1",
	"body": "Choose the option nearest in meaning to the word(s) or phrase in italics (**).\n\nThe Conference Centre caters for *transients* only.",
	"options": {
		"a": "temporary guests",
		"b": "professionals",
		"c": "permanent guests"
	},
	"answer": "a"
}
]